githubutils/__init__.py
githubutils/ghauth.py
githubutils/github.py
githubutils/travis.py
minerutils/__init__.py
minerutils/auth.py
minerutils/github.py
minerutils/travis.py
MinerUtils-2.0.5.dist-info/LICENSE.md
MinerUtils-2.0.5.dist-info/METADATA
MinerUtils-2.0.5.dist-info/WHEEL
MinerUtils-2.0.5.dist-info/top_level.txt
MinerUtils-2.0.5.dist-info/RECORD
